[
  {
    "type": "birthday",
    "emoji": "🎂",
    "accent": "#FFB72B",
    "gradient": "linear-gradient(135deg, #FFB72B 0%, #FFCC66 100%)",
    "title": "Happy Birthday!",
    "name": "* Kanstantsin Shuryhin",
    "date": "April 27",
    "message": "Wishing you an amazing day filled with joy and celebration!",
    "teamNote": "* Mediation: Customer Success A&amp;F · * Belarus"
  },
  {
    "type": "officelife",
    "emoji": "📢",
    "accent": "#00FFD1",
    "gradient": "linear-gradient(135deg, #00FFD1 0%, #99FFEC 100%)",
    "title": "From #general",
    "headline": "Hi everyone ! We’ve just published the LinkedIn post for the upcoming Barcelona ...",
    "quote": "Hi everyone ! We’ve just published the LinkedIn post for the upcoming Barcelona Data Night (May 14) - feel free to check it out and support click! This time we’ll have our colleagues and speaking, along with an external guest Daniel Sogl (Thinktecture) - it’s going to be a great mix of practical ins",
    "author": "Katarzyna Raniszewska",
    "reactions": "",
    "channel": "#general"
  },
  {
    "type": "officelife",
    "emoji": "📢",
    "accent": "#00FFD1",
    "gradient": "linear-gradient(135deg, #00FFD1 0%, #99FFEC 100%)",
    "title": "From #general",
    "headline": "Team — I’ve drafted a north-star document on how we approach learning integratio...",
    "quote": "Team — I’ve drafted a north-star document on how we approach learning integration at Appodeal. It connects the WIG, our culture work, and the AI adoption strategy into one system. Doc: Learnings Integration at Appodeal This is a draft. I want everyone — engineering, HR, management, ICs — to read it ",
    "author": "Pavel Golubev",
    "reactions": "",
    "channel": "#general"
  },
  {
    "type": "officelife",
    "emoji": "📢",
    "accent": "#00FFD1",
    "gradient": "linear-gradient(135deg, #00FFD1 0%, #99FFEC 100%)",
    "title": "From #general",
    "headline": "Two OKR decisions — effective immediately: 1. We’re retiring the term “Rocks.” G...",
    "quote": "Two OKR decisions — effective immediately: 1. We’re retiring the term “Rocks.” Going forward, we use Key Results (KRs) only. Let’s rename Key results where we have word “Rocks” by the end of the week. 2. Every objective should have a maximum of 5 KRs.",
    "author": "Alexandr Zhitlukhin",
    "reactions": "",
    "channel": "#general"
  },
  {
    "type": "officelife",
    "emoji": "👏",
    "accent": "#5D2CAC",
    "gradient": "linear-gradient(135deg, #5D2CAC 0%, #8B5DD5 100%)",
    "title": "From #claps",
    "headline": "Dario Hernandez received 50× from Roman de las Heras",
    "quote": "Dario Hernandez received 50× from Roman de las Heras",
    "author": "Clappy",
    "reactions": "",
    "channel": "#claps"
  },
  {
    "type": "officelife",
    "emoji": "👏",
    "accent": "#5D2CAC",
    "gradient": "linear-gradient(135deg, #5D2CAC 0%, #8B5DD5 100%)",
    "title": "From #claps",
    "headline": "Emma received 10× from Alina Li",
    "quote": "Emma received 10× from Alina Li",
    "author": "Clappy",
    "reactions": "",
    "channel": "#claps"
  }
]